racs/__init__.py
racs/client.py
racs/command.py
racs/excpetion.py
racs/frame.py
racs/pack.py
racs/pipeline.py
racs/socket.py
racs/stream.py
racs/utils.py
racs-0.1.2.dist-info/licenses/LICENSE
racs-0.1.2.dist-info/METADATA
racs-0.1.2.dist-info/WHEEL
racs-0.1.2.dist-info/top_level.txt
racs-0.1.2.dist-info/RECORD
