Metadata-Version: 2.4
Name: racs
Version: 0.1.2
Summary: Python client library for RACS
License: MIT
Classifier: Programming Language :: Python :: 3
Classifier: Operating System :: OS Independent
Requires-Python: >=3.9
License-File: LICENSE
Requires-Dist: msgpack
Requires-Dist: crc32c
Requires-Dist: mmh3
Requires-Dist: zstd
Dynamic: classifier
Dynamic: description
Dynamic: description-content-type
Dynamic: license
Dynamic: license-file
Dynamic: requires-dist
Dynamic: requires-python
Dynamic: summary
